[
    {
        "rating": "4.5",
        "title": "The Water Cure",
        "text": "Martin Hyatt",
        "img": "img/moon.png",
        "audio": "voice.mp3"
    },
    {
        "rating": "4.5",
        "title": "The Water Cure",
        "text": "Martin Hyatt",
        "img": "img/moon.png",
        "audio": "voice.mp3"
    },
    {
        "rating": "4.5",
        "title": "The Water Cure",
        "text": "Martin Hyatt",
        "img": "img/moon.png",
        "audio": "voice.mp3"
    },
    {
        "rating": "4.5",
        "title": "The Water Cure",
        "text": "Martin Hyatt",
        "img": "img/moon.png",
        "audio": "voice.mp3"
    },
    {
        "rating": "4.5",
        "title": "The Water Cure",
        "text": "Martin Hyatt",
        "img": "img/moon.png",
        "audio": "voice.mp3"
    },
    {
        "rating": "4.5",
        "title": "The Water Cure",
        "text": "Martin Hyatt",
        "img": "img/moon.png",
        "audio": "voice.mp3"
    },
    {
        "rating": "4.5",
        "title": "The Water Cure",
        "text": "Martin Hyatt",
        "img": "img/moon.png",
        "audio": "voice.mp3"
    }
]